Metadata-Version: 2.1
Name: trex-mail
Version: 0.1.11
Summary: TRex Core library package
Home-page: https://bitbucket.org/lokjac/trex-mail
Author: Jack Lok
Author-email: sglok77@gmail.com
Classifier: Programming Language :: Python :: 3
Classifier: License :: OSI Approved :: MIT License
Classifier: Operating System :: OS Independent
License-File: LICENSE
